<annotation>
	<folder></folder>
	<filename>571_jpg.rf.934a26e214d2e773f7b522b05aa74cc8.jpg</filename>
	<path>571_jpg.rf.934a26e214d2e773f7b522b05aa74cc8.jpg</path>
	<source>
		<database>roboflow.ai</database>
	</source>
	<size>
		<width>992</width>
		<height>744</height>
		<depth>3</depth>
	</size>
	<segmented>0</segmented>
	<object>
		<name>Fire</name>
		<pose>Unspecified</pose>
		<truncated>0</truncated>
		<difficult>0</difficult>
		<occluded>0</occluded>
		<bndbox>
			<xmin>138</xmin>
			<xmax>585</xmax>
			<ymin>197</ymin>
			<ymax>600</ymax>
		</bndbox>
	</object>
</annotation>
