<annotation>
	<folder></folder>
	<filename>MirrorWEBFire258_jpg.rf.523b6dab0a08a930eb23bede5b615681.jpg</filename>
	<path>MirrorWEBFire258_jpg.rf.523b6dab0a08a930eb23bede5b615681.jpg</path>
	<source>
		<database>roboflow.ai</database>
	</source>
	<size>
		<width>1280</width>
		<height>720</height>
		<depth>3</depth>
	</size>
	<segmented>0</segmented>
	<object>
		<name>Fire</name>
		<pose>Unspecified</pose>
		<truncated>0</truncated>
		<difficult>0</difficult>
		<occluded>0</occluded>
		<bndbox>
			<xmin>967</xmin>
			<xmax>1084</xmax>
			<ymin>426</ymin>
			<ymax>508</ymax>
		</bndbox>
	</object>
	<object>
		<name>Fire</name>
		<pose>Unspecified</pose>
		<truncated>0</truncated>
		<difficult>0</difficult>
		<occluded>0</occluded>
		<bndbox>
			<xmin>713</xmin>
			<xmax>755</xmax>
			<ymin>264</ymin>
			<ymax>303</ymax>
		</bndbox>
	</object>
	<object>
		<name>Fire</name>
		<pose>Unspecified</pose>
		<truncated>0</truncated>
		<difficult>0</difficult>
		<occluded>0</occluded>
		<bndbox>
			<xmin>713</xmin>
			<xmax>733</xmax>
			<ymin>335</ymin>
			<ymax>351</ymax>
		</bndbox>
	</object>
	<object>
		<name>Fire</name>
		<pose>Unspecified</pose>
		<truncated>0</truncated>
		<difficult>0</difficult>
		<occluded>0</occluded>
		<bndbox>
			<xmin>613</xmin>
			<xmax>634</xmax>
			<ymin>269</ymin>
			<ymax>300</ymax>
		</bndbox>
	</object>
</annotation>
